LICENSE
MANIFEST.in
README.rst
setup.py
bin/templet
templet/__init__.py
templet/utils.py
templet.egg-info/PKG-INFO
templet.egg-info/SOURCES.txt
templet.egg-info/dependency_links.txt
templet.egg-info/requires.txt
templet.egg-info/top_level.txt