Metadata-Version: 1.0
Name: templet
Version: 0.4.0
Summary: Simple scaffolding tool
Home-page: git://skurih.in/templet.git
Author: Alexandr Skurikhin
Author-email: a@skurih.in
License: Copyright (c) 2013 Alexandr Skurikhin
